ohttpy-0.1a13.dist-info/METADATA
ohttpy-0.1a13.dist-info/WHEEL
ohttpy/session.py
ohttpy/transport.py
ohttpy/_generators.py
ohttpy/__init__.py
ohttpy/ohttpy.pyd
ohttpy-0.1a13.dist-info/RECORD
