Metadata-Version: 2.4
Name: ohttpy
Version: 0.1a13
Classifier: Programming Language :: Rust
Classifier: Programming Language :: Python :: Implementation :: CPython
Classifier: Programming Language :: Python :: Implementation :: PyPy
Classifier: Programming Language :: Python :: 3
Requires-Dist: httpx>=0.27,<0.99
Requires-Dist: requests>=2.22,<2.99
Summary: A package that allows for client-side OHTTP-wrapping over HTTP communication
Author-email: Lorica Cybersecurity <support@loricacyber.com>
Requires-Python: >=3.7
